cybersailor/__init__.py
cybersailor/logger.py
cybersailor/sdk.py
cybersailor/sqs_listener.py
cybersailor/sqs_message.py
cybersailor/watch_renewal.py
cybersailor-0.1.15.dist-info/METADATA
cybersailor-0.1.15.dist-info/WHEEL
cybersailor-0.1.15.dist-info/top_level.txt
cybersailor-0.1.15.dist-info/RECORD
