Metadata-Version: 2.1
Name: cybersailor
Version: 0.1.15
Summary: Cybersailor Python SDK
Author: Carthooks
Author-email: developer@carthooks.com
License: MIT
Classifier: Programming Language :: Python :: 3
Classifier: License :: OSI Approved :: MIT License
Requires-Dist: carthooks >=0.1.8
Requires-Dist: boto3 >=1.26.0
